my_ui_booking/__init__.py
my_ui_booking/booking.py
my_ui_booking/constants.py
my_ui_booking.com-0.5.dist-info/METADATA
my_ui_booking.com-0.5.dist-info/WHEEL
my_ui_booking.com-0.5.dist-info/top_level.txt
my_ui_booking.com-0.5.dist-info/RECORD
