Metadata-Version: 2.1
Name: my-ui-booking.com
Version: 0.5
Summary: 5th release of my package
Author: Arijit Das
